tradier_python/__init__.py
tradier_python/models.py
tradier_python/tradier_api.py
tradier_python/.mypy_cache/.gitignore
tradier_python/.mypy_cache/CACHEDIR.TAG
tradier_python/.mypy_cache/missing_stubs
tradier_python/.mypy_cache/3.10/@plugins_snapshot.json
tradier_python/.mypy_cache/3.10/_ast.data.json
tradier_python/.mypy_cache/3.10/_ast.meta.json
tradier_python/.mypy_cache/3.10/_collections_abc.data.json
tradier_python/.mypy_cache/3.10/_collections_abc.meta.json
tradier_python/.mypy_cache/3.10/_thread.data.json
tradier_python/.mypy_cache/3.10/_thread.meta.json
tradier_python/.mypy_cache/3.10/_warnings.data.json
tradier_python/.mypy_cache/3.10/_warnings.meta.json
tradier_python/.mypy_cache/3.10/_weakref.data.json
tradier_python/.mypy_cache/3.10/_weakref.meta.json
tradier_python/.mypy_cache/3.10/_weakrefset.data.json
tradier_python/.mypy_cache/3.10/_weakrefset.meta.json
tradier_python/.mypy_cache/3.10/abc.data.json
tradier_python/.mypy_cache/3.10/abc.meta.json
tradier_python/.mypy_cache/3.10/array.data.json
tradier_python/.mypy_cache/3.10/array.meta.json
tradier_python/.mypy_cache/3.10/ast.data.json
tradier_python/.mypy_cache/3.10/ast.meta.json
tradier_python/.mypy_cache/3.10/builtins.data.json
tradier_python/.mypy_cache/3.10/builtins.meta.json
tradier_python/.mypy_cache/3.10/codecs.data.json
tradier_python/.mypy_cache/3.10/codecs.meta.json
tradier_python/.mypy_cache/3.10/colorsys.data.json
tradier_python/.mypy_cache/3.10/colorsys.meta.json
tradier_python/.mypy_cache/3.10/contextlib.data.json
tradier_python/.mypy_cache/3.10/contextlib.meta.json
tradier_python/.mypy_cache/3.10/copy.data.json
tradier_python/.mypy_cache/3.10/copy.meta.json
tradier_python/.mypy_cache/3.10/dataclasses.data.json
tradier_python/.mypy_cache/3.10/dataclasses.meta.json
tradier_python/.mypy_cache/3.10/datetime.data.json
tradier_python/.mypy_cache/3.10/datetime.meta.json
tradier_python/.mypy_cache/3.10/decimal.data.json
tradier_python/.mypy_cache/3.10/decimal.meta.json
tradier_python-0.1.3.dist-info/LICENSE
tradier_python-0.1.3.dist-info/METADATA
tradier_python-0.1.3.dist-info/WHEEL
tradier_python-0.1.3.dist-info/top_level.txt
tradier_python-0.1.3.dist-info/RECORD
