Metadata-Version: 2.1
Name: tradier-python
Version: 0.1.3
Summary: Tradier API client implemented in python
Home-page: https://github.com/phileaton/tradier-python
Author: Philip Eaton
License: MIT License
Platform: UNKNOWN
Classifier: License :: OSI Approved :: MIT License
Classifier: Programming Language :: Python :: 3
Classifier: Development Status :: 2 - Pre-Alpha
License-File: LICENSE
Requires-Dist: requests
Requires-Dist: pydantic
